datalib/__init__.py
datalib/data_processing.py
datalib/statistics.py
datalib/utils.py
datalib/visualization.py
datalib_sghaier_project-0.1.1.dist-info/METADATA
datalib_sghaier_project-0.1.1.dist-info/WHEEL
datalib_sghaier_project-0.1.1.dist-info/top_level.txt
datalib_sghaier_project-0.1.1.dist-info/RECORD
