Metadata-Version: 2.1
Name: datalib_sghaier_project
Version: 0.1.1
Summary: A Python library for data manipulation and analysis.
Home-page: https://github.com/MazenSghaier/datalib
Author: Mazen Sghaier
Author-email: sghaiermazen7@gmail.com
Classifier: Programming Language :: Python :: 3
Classifier: License :: OSI Approved :: MIT License
Classifier: Operating System :: OS Independent
Requires-Python: >=3.8
Requires-Dist: numpy>=1.21.0
Requires-Dist: pandas>=1.3.0
Requires-Dist: matplotlib>=3.4.0
Requires-Dist: scikit-learn>=0.24.0
